README.txt
cvt.py
setup.py
matricks/__init__.py
matricks/__main__.py
matricks/conversion.py
matricks/distance.py
matricks/timing.py
matricks/util.py
matricks.egg-info/PKG-INFO
matricks.egg-info/SOURCES.txt
matricks.egg-info/dependency_links.txt
matricks.egg-info/entry_points.txt
matricks.egg-info/requires.txt
matricks.egg-info/top_level.txt
matricks.egg-info/zip-safe
matricks/scoring/__init__.py
matricks/scoring/choi.py
matricks/scoring/dict.py
matricks/scoring/godel.py
matricks/scoring/hilo.py
matricks/scoring/modal.py
matricks/scoring/pearson.py
matricks/scoring/positional.py
matricks/scoring/primes.py
matricks/scoring/scorer.py