Metadata-Version: 1.0
Name: matricks
Version: 0.3.20
Summary: manipulate datasets encoded as 2-D matrices with annotation (first) row and (first) column
Home-page: http://pypi.python.org/pypi/matricks/
Author: Nick Seidenman
Author-email: seidenman@wehi.edu.au
License: UNKNOWN
Keywords: dataset manipulation algebra bioinformatics
Platform: UNKNOWN
Classifier: Development Status :: 4 - Beta
Classifier: Environment :: Console
Classifier: Topic :: Scientific/Engineering :: Bio-Informatics
Classifier: Topic :: Scientific/Engineering :: Information Analysis
Classifier: License :: OSI Approved :: BSD License
